apigtool/auth_state.py
apigtool/command.py
apigtool/utility.py
APIGtool-0.3.0.dist-info/METADATA
APIGtool-0.3.0.dist-info/WHEEL
APIGtool-0.3.0.dist-info/entry_points.txt
APIGtool-0.3.0.dist-info/top_level.txt
APIGtool-0.3.0.dist-info/RECORD
